MANIFEST.in
README
VERSION
setup.cfg
setup.py
HTSeq/StepVector.py
HTSeq/_HTSeq_internal.py
HTSeq/__init__.py
HTSeq/_version.py
HTSeq/scripts/__init__.py
HTSeq/scripts/count.py
HTSeq/scripts/qa.py
HTSeq_arm_linux.egg-info/PKG-INFO
HTSeq_arm_linux.egg-info/SOURCES.txt
HTSeq_arm_linux.egg-info/dependency_links.txt
HTSeq_arm_linux.egg-info/top_level.txt
scripts/htseq-count
scripts/htseq-qa
src/StepVector_wrap.cxx
src/_HTSeq.c
src/step_vector.h